{
  "rows": [
    {
      "caseId": "general_gt",
      "setup": {
        "caseId": "general_gt",
        "subjectId": "general_reading",
        "interpretationThemeId": "auto",
        "spreadType": "grand-tableau",
        "question": "What should I know about the next three months overall?",
        "threeCardMode": "past-present-future",
        "significatorMode": "open"
      },
      "resolvedSubjectId": "love",
      "resolvedThemeId": "new_connection",
      "resolvedThemeLabel": "New Connection",
      "selectedEntries": [
        {
          "technique": "card",
          "entryId": "card:love:24",
          "techniqueKey": "card:24",
          "score": 14.134,
          "selectedText": "Heart in Love highlights values and emotional truth guide choices.",
          "summary": "Heart emphasizes love in this context.",
          "alternatives": []
        },
        {
          "technique": "house",
          "entryId": "house:love:1",
          "techniqueKey": "house:1",
          "score": 11.828,
          "selectedText": "Rider House centers incoming momentum in a Love frame.",
          "summary": "Rider House acts as a contextual anchor.",
          "alternatives": []
        },
        {
          "technique": "pair",
          "entryId": "pair:love:17-27:fallback",
          "techniqueKey": "pair:17-27",
          "score": 12.472,
          "selectedText": "Stork + Letter blends change with document, inviting sequence improvements deliberately while staying aware of vague or untracked communication.",
          "summary": "Stork and Letter create a contextual pair bridge.",
          "alternatives": []
        },
        {
          "technique": "diagonal",
          "entryId": "diagonal:love:primary",
          "techniqueKey": "diagonal:primary",
          "score": 9.84,
          "selectedText": "The primary diagonal in Love reveals a storyline crossing immediate and long-range influences.",
          "summary": null,
          "alternatives": []
        },
        {
          "technique": "knighting",
          "entryId": "knighting:love:significator",
          "techniqueKey": "knighting:significator",
          "score": 9.346,
          "selectedText": "Knighting from significator in Love highlights indirect triggers that can shift timing.",
          "summary": null,
          "alternatives": []
        },
        {
          "technique": "proximity",
          "entryId": "proximity:love:near",
          "techniqueKey": "proximity:near",
          "score": 10.178,
          "selectedText": "In Love, near proximity indicates how urgently this influence should be handled.",
          "summary": null,
          "alternatives": []
        },
        {
          "technique": "significator",
          "entryId": "significator:love:open",
          "techniqueKey": "significator:open",
          "score": 10.772,
          "selectedText": "Significator mode open in Love defines perspective and role framing before interpretation.",
          "summary": null,
          "alternatives": []
        }
      ],
      "rankingConcerns": [],
      "weakSummaryLines": [
        "Taken as a whole, this reads as a living process in the dynamic between you and the counterpart, where pacing and consistency matter more than force."
      ],
      "repeatedPhrasesInReading": [],
      "finalText": "Using Love as the primary lens with a new connection emphasis, this Grand Tableau addresses \"What should I know about the next three months overall\". The tableau centers on Counterpart (28) in Garden House. At this position, the message is that the significant other perspective enters the reading, and the wider layer suggests that partnership dynamics require mutual clarity. Closest to center, Stork (17) beside Scythe (10) suggests this: a blend of change and cut; sequence improvements deliberately, while keeping in mind reactive or harsh decisions; this pair matters because it shows how two active themes combine in real time. Secondary structure appears across Stork (17), Counterpart (28), Tower (19) and Ring (25), Anchor (35), Dog (18), and knight links to Heart (24), Sun (31), Coffin (8), Key (33) imply that outcomes depend on sequence; diagonal links show continuity across cards that seem unrelated at first. Timing-wise, Stork (17), Letter (27), Anchor (35), Scythe (10) describe what is immediate, while Heart (24), Bear (15), Sun (31), Ring (25) are more likely to shape the next wave. Taken as a whole, this reads as a living process in the dynamic between you and the counterpart, where pacing and consistency matter more than force. Choose one honest conversation and let the response set your next step. ",
      "wordCount": 214
    },
    {
      "caseId": "general_3card",
      "setup": {
        "caseId": "general_3card",
        "subjectId": "general_reading",
        "interpretationThemeId": "clarity",
        "spreadType": "three-card",
        "question": "What is the clearest way to approach this week?",
        "threeCardMode": "situation-challenge-advice",
        "significatorMode": "self"
      },
      "resolvedSubjectId": "health",
      "resolvedThemeId": "rest",
      "resolvedThemeLabel": "Rest",
      "selectedEntries": [
        {
          "technique": "card",
          "entryId": "card:health:28",
          "techniqueKey": "card:28",
          "score": 12.334,
          "selectedText": "Counterpart in Health highlights the significant other perspective enters the reading.",
          "summary": "Counterpart emphasizes other in this context.",
          "alternatives": []
        },
        {
          "technique": "pair",
          "entryId": "pair:health:22-28:fallback",
          "techniqueKey": "pair:22-28",
          "score": 12.428,
          "selectedText": "Crossroads + Counterpart blends choice with other, suggesting choose the path aligned with values while staying aware of projecting assumptions onto others.",
          "summary": "Crossroads and Counterpart create a contextual pair bridge.",
          "alternatives": []
        },
        {
          "technique": "diagonal",
          "entryId": "diagonal:health:primary",
          "techniqueKey": "diagonal:primary",
          "score": 9.84,
          "selectedText": "The primary diagonal in Health reveals a storyline crossing immediate and long-range influences.",
          "summary": null,
          "alternatives": []
        },
        {
          "technique": "knighting",
          "entryId": "knighting:health:significator",
          "techniqueKey": "knighting:significator",
          "score": 9.346,
          "selectedText": "Knighting from significator in Health highlights indirect triggers that can shift timing.",
          "summary": null,
          "alternatives": []
        },
        {
          "technique": "proximity",
          "entryId": "proximity:health:near",
          "techniqueKey": "proximity:near",
          "score": 10.178,
          "selectedText": "In Health, near proximity indicates how urgently this influence should be handled.",
          "summary": null,
          "alternatives": []
        },
        {
          "technique": "significator",
          "entryId": "significator:health:self",
          "techniqueKey": "significator:self",
          "score": 10.772,
          "selectedText": "Significator mode self in Health defines perspective and role framing before interpretation.",
          "summary": null,
          "alternatives": []
        }
      ],
      "rankingConcerns": [],
      "weakSummaryLines": [],
      "repeatedPhrasesInReading": [],
      "finalText": "Your question, \"What is the clearest way to approach this week\", is read here through a Health lens with a rest emphasis. The first position, Situation, lands on Counterpart (28), so the immediate message is that consider how the other party experiences this; reading this as a timeline prevents over-weighting any single card. Challenge carries Crossroads (22), and this pivot highlights that multiple paths require explicit criteria, where one small adjustment can shift the whole trajectory. Advice closes with Bear (15), and the directional message is that strength can protect if paired with fairness when the pivot receives consistent attention. A clear subtext emerges through Counterpart (28) with Crossroads (22): choice with other, suggesting choose the path aligned with values while staying aware of projecting assumptions onto others, which gives the reading a coherent practical arc. Commit to one practical move and review the result before deciding further. ",
      "wordCount": 148
    },
    {
      "caseId": "love_gt",
      "setup": {
        "caseId": "love_gt",
        "subjectId": "love",
        "interpretationThemeId": "commitment",
        "spreadType": "grand-tableau",
        "question": "How is this relationship developing and what needs care?",
        "threeCardMode": "past-present-future",
        "significatorMode": "relationship"
      },
      "resolvedSubjectId": "love",
      "resolvedThemeId": "commitment",
      "resolvedThemeLabel": "Commitment",
      "selectedEntries": [
        {
          "technique": "card",
          "entryId": "card:love:4",
          "techniqueKey": "card:4",
          "score": 12.334,
          "selectedText": "House in Love highlights stability and foundations become central.",
          "summary": "House emphasizes home in this context.",
          "alternatives": []
        },
        {
          "technique": "house",
          "entryId": "house:love:1",
          "techniqueKey": "house:1",
          "score": 11.828,
          "selectedText": "Rider House centers incoming momentum in a Love frame.",
          "summary": "Rider House acts as a contextual anchor.",
          "alternatives": []
        },
        {
          "technique": "pair",
          "entryId": "pair:love:7-27:fallback",
          "techniqueKey": "pair:7-27",
          "score": 12.472,
          "selectedText": "Snake + Letter blends strategy with document, inviting separate signal from social noise while staying aware of vague or untracked communication.",
          "summary": "Snake and Letter create a contextual pair bridge.",
          "alternatives": []
        },
        {
          "technique": "diagonal",
          "entryId": "diagonal:love:primary",
          "techniqueKey": "diagonal:primary",
          "score": 9.84,
          "selectedText": "The primary diagonal in Love reveals a storyline crossing immediate and long-range influences.",
          "summary": null,
          "alternatives": []
        },
        {
          "technique": "knighting",
          "entryId": "knighting:love:significator",
          "techniqueKey": "knighting:significator",
          "score": 9.346,
          "selectedText": "Knighting from significator in Love highlights indirect triggers that can shift timing.",
          "summary": null,
          "alternatives": []
        },
        {
          "technique": "proximity",
          "entryId": "proximity:love:near",
          "techniqueKey": "proximity:near",
          "score": 10.178,
          "selectedText": "In Love, near proximity indicates how urgently this influence should be handled.",
          "summary": null,
          "alternatives": []
        },
        {
          "technique": "significator",
          "entryId": "significator:love:relationship",
          "techniqueKey": "significator:relationship",
          "score": 10.772,
          "selectedText": "Significator mode relationship in Love defines perspective and role framing before interpretation.",
          "summary": null,
          "alternatives": []
        }
      ],
      "rankingConcerns": [],
      "weakSummaryLines": [
        "Overall, the pattern suggests a calm cumulative shift in the relationship itself, with steady choices outperforming dramatic moves."
      ],
      "repeatedPhrasesInReading": [],
      "finalText": "\"How is this relationship developing and what needs care\" comes into focus through Love in this Grand Tableau, with a commitment emphasis. From Letter House, Querent (29) frames the reading around the querent's agency and orientation. In context, the spread also suggests that self-awareness improves relational clarity. A strong local signal comes from Snake (7) and Letter (27), pointing toward this dynamic: a blend of strategy and document; separate signal from social noise, while keeping in mind vague or untracked communication; this pair matters because it shows how two active themes combine in real time. In the background, diagonals through Book (26), Snake (7), Querent (29) and Mountain (21), plus knighting links at Key (33), Fish (34), Ship (3), show a process unfolding in stages rather than a single pivot. Timing-wise, Snake (7), Letter (27), Rider (1), Mountain (21) describe what is immediate, while Book (26), Key (33), Garden (20), Fish (34) are more likely to shape the next wave; proximity keeps the timing clear: immediate pressure first, broader movement second. Overall, the pattern suggests a calm cumulative shift in the relationship itself, with steady choices outperforming dramatic moves. Ask one direct question and let the answer shape what comes next. ",
      "wordCount": 201
    },
    {
      "caseId": "love_3card",
      "setup": {
        "caseId": "love_3card",
        "subjectId": "love",
        "interpretationThemeId": "communication",
        "spreadType": "three-card",
        "question": "What should I focus on in my current romantic dynamic?",
        "threeCardMode": "situation-challenge-advice",
        "significatorMode": "relationship"
      },
      "resolvedSubjectId": "love",
      "resolvedThemeId": "communication",
      "resolvedThemeLabel": "Communication",
      "selectedEntries": [
        {
          "technique": "card",
          "entryId": "card:love:12",
          "techniqueKey": "card:12",
          "score": 14.134,
          "selectedText": "Birds in Love highlights conversation and anxiety move in tandem.",
          "summary": "Birds emphasizes dialogue in this context.",
          "alternatives": []
        },
        {
          "technique": "pair",
          "entryId": "pair:love:6-12:fallback",
          "techniqueKey": "pair:6-12",
          "score": 12.472,
          "selectedText": "Clouds + Birds blends uncertainty with dialogue, inviting name unknowns before choosing direction while staying aware of amplifying rumor or speculation.",
          "summary": "Clouds and Birds create a contextual pair bridge.",
          "alternatives": []
        },
        {
          "technique": "diagonal",
          "entryId": "diagonal:love:primary",
          "techniqueKey": "diagonal:primary",
          "score": 10.47,
          "selectedText": "The primary diagonal in Love reveals a storyline crossing immediate and long-range influences.",
          "summary": null,
          "alternatives": []
        },
        {
          "technique": "knighting",
          "entryId": "knighting:love:significator",
          "techniqueKey": "knighting:significator",
          "score": 9.976,
          "selectedText": "Knighting from significator in Love highlights indirect triggers that can shift timing.",
          "summary": null,
          "alternatives": []
        },
        {
          "technique": "proximity",
          "entryId": "proximity:love:near",
          "techniqueKey": "proximity:near",
          "score": 10.178,
          "selectedText": "In Love, near proximity indicates how urgently this influence should be handled.",
          "summary": null,
          "alternatives": []
        },
        {
          "technique": "significator",
          "entryId": "significator:love:relationship",
          "techniqueKey": "significator:relationship",
          "score": 11.312,
          "selectedText": "Significator mode relationship in Love defines perspective and role framing before interpretation.",
          "summary": null,
          "alternatives": []
        }
      ],
      "rankingConcerns": [],
      "weakSummaryLines": [],
      "repeatedPhrasesInReading": [],
      "finalText": "\"What should I focus on in my current romantic dynamic\" comes into focus through Love in this 3-card, with a communication emphasis. What starts this sequence is Situation with Birds (12), bringing small talks and check-ins restore emotional safety directly to the front of the reading. Challenge carries Clouds (6), and this pivot highlights that clarity is partial and conditions are shifting, where one small adjustment can shift the whole trajectory; the middle position is especially important for how the outcome develops. Future movement in Advice and Child (13) points to this: gentle curiosity can reopen trust, provided the central pressure is handled honestly. A clear subtext emerges through Birds (12) with Clouds (6): a blend of dialogue and uncertainty; favor concise, clarifying dialogue, while keeping in mind making absolute claims too early, which gives the reading a coherent practical arc. Ask one direct question and let the answer shape what comes next. ",
      "wordCount": 153
    },
    {
      "caseId": "work_gt",
      "setup": {
        "caseId": "work_gt",
        "subjectId": "work",
        "interpretationThemeId": "burnout",
        "spreadType": "grand-tableau",
        "question": "How can I navigate workload pressure and politics at work?",
        "threeCardMode": "past-present-future",
        "significatorMode": "self"
      },
      "resolvedSubjectId": "work",
      "resolvedThemeId": "burnout",
      "resolvedThemeLabel": "Burnout",
      "selectedEntries": [
        {
          "technique": "card",
          "entryId": "card:work:12",
          "techniqueKey": "card:12",
          "score": 14.134,
          "selectedText": "Birds in Work highlights conversation and anxiety move in tandem.",
          "summary": "Birds emphasizes dialogue in this context.",
          "alternatives": []
        },
        {
          "technique": "house",
          "entryId": "house:work:1",
          "techniqueKey": "house:1",
          "score": 11.828,
          "selectedText": "Rider House centers incoming momentum in a Work frame.",
          "summary": "Rider House acts as a contextual anchor.",
          "alternatives": []
        },
        {
          "technique": "pair",
          "entryId": "pair:work:3-30:fallback",
          "techniqueKey": "pair:3-30",
          "score": 12.472,
          "selectedText": "Ship + Lily blends journey with maturity, inviting define direction before committing resources while staying aware of passive avoidance of necessary action.",
          "summary": "Ship and Lily create a contextual pair bridge.",
          "alternatives": []
        },
        {
          "technique": "diagonal",
          "entryId": "diagonal:work:primary",
          "techniqueKey": "diagonal:primary",
          "score": 9.84,
          "selectedText": "The primary diagonal in Work reveals a storyline crossing immediate and long-range influences.",
          "summary": null,
          "alternatives": []
        },
        {
          "technique": "knighting",
          "entryId": "knighting:work:significator",
          "techniqueKey": "knighting:significator",
          "score": 9.976,
          "selectedText": "Knighting from significator in Work highlights indirect triggers that can shift timing.",
          "summary": null,
          "alternatives": []
        },
        {
          "technique": "proximity",
          "entryId": "proximity:work:near",
          "techniqueKey": "proximity:near",
          "score": 10.898,
          "selectedText": "In Work, near proximity indicates how urgently this influence should be handled.",
          "summary": null,
          "alternatives": []
        },
        {
          "technique": "significator",
          "entryId": "significator:work:self",
          "techniqueKey": "significator:self",
          "score": 10.772,
          "selectedText": "Significator mode self in Work defines perspective and role framing before interpretation.",
          "summary": null,
          "alternatives": []
        }
      ],
      "rankingConcerns": [],
      "weakSummaryLines": [],
      "repeatedPhrasesInReading": [],
      "finalText": "\"How can I navigate workload pressure and politics at work\" comes into focus through Work in this Grand Tableau, with a burnout emphasis. From Anchor House, Querent (29) frames the reading around the querent's agency and orientation. In context, the spread also suggests that professional identity and priorities need definition. A strong local signal comes from Lily (30) and Ship (3), pointing toward this dynamic: a blend of maturity and journey; pair composure with clear intent, while keeping in mind drifting without destination; read the pair as one sentence: one card sets pressure, the other names response; the pair gives practical context that keeps interpretation grounded. Secondary structure appears across Tower (19), Bouquet (9), Lily (30), Querent (29) and Tree (5), and knight links to Snake (7), Book (26), Scythe (10) imply that outcomes depend on sequence. Read Lily (30), Ship (3), Tree (5), Cross (36) as present-tense influence and Bouquet (9), Snake (7), Counterpart (28), Book (26) as the sequence that forms right behind it. Seen together, these signals describe progression rather than verdict, and the meaning sharpens as events unfold. Make one practical process change and measure results before adding more. ",
      "wordCount": 193
    },
    {
      "caseId": "work_3card",
      "setup": {
        "caseId": "work_3card",
        "subjectId": "work",
        "interpretationThemeId": "workplace_politics",
        "spreadType": "three-card",
        "question": "What is happening in my team dynamics this month?",
        "threeCardMode": "situation-challenge-advice",
        "significatorMode": "self"
      },
      "resolvedSubjectId": "work",
      "resolvedThemeId": "workplace_politics",
      "resolvedThemeLabel": "Workplace Politics",
      "selectedEntries": [
        {
          "technique": "card",
          "entryId": "card:work:28",
          "techniqueKey": "card:28",
          "score": 12.334,
          "selectedText": "Counterpart in Work highlights the significant other perspective enters the reading.",
          "summary": "Counterpart emphasizes other in this context.",
          "alternatives": []
        },
        {
          "technique": "pair",
          "entryId": "pair:work:14-28:fallback",
          "techniqueKey": "pair:14-28",
          "score": 12.406,
          "selectedText": "Fox + Counterpart in work context indicates quality control and strategic positioning matter and key counterpart stakeholders shape outcomes.",
          "summary": "Fox and Counterpart create a contextual pair bridge.",
          "alternatives": []
        },
        {
          "technique": "diagonal",
          "entryId": "diagonal:work:primary",
          "techniqueKey": "diagonal:primary",
          "score": 10.47,
          "selectedText": "The primary diagonal in Work reveals a storyline crossing immediate and long-range influences.",
          "summary": null,
          "alternatives": []
        },
        {
          "technique": "knighting",
          "entryId": "knighting:work:significator",
          "techniqueKey": "knighting:significator",
          "score": 9.346,
          "selectedText": "Knighting from significator in Work highlights indirect triggers that can shift timing.",
          "summary": null,
          "alternatives": []
        },
        {
          "technique": "proximity",
          "entryId": "proximity:work:near",
          "techniqueKey": "proximity:near",
          "score": 10.178,
          "selectedText": "In Work, near proximity indicates how urgently this influence should be handled.",
          "summary": null,
          "alternatives": []
        },
        {
          "technique": "significator",
          "entryId": "significator:work:self",
          "techniqueKey": "significator:self",
          "score": 11.312,
          "selectedText": "Significator mode self in Work defines perspective and role framing before interpretation.",
          "summary": null,
          "alternatives": []
        }
      ],
      "rankingConcerns": [
        {
          "type": "pair",
          "message": "A stronger pair candidate scored higher than the selected pair context.",
          "selectedKey": "14-28",
          "strongerKey": "7-14",
          "delta": 1.168
        }
      ],
      "weakSummaryLines": [],
      "repeatedPhrasesInReading": [],
      "finalText": "Your question, \"What is happening in my team dynamics this month\", is read here through a Work lens with a workplace politics emphasis. The opening card in Situation is Counterpart (28), and its message is that key counterpart stakeholders shape outcomes. Challenge carries Fox (14), and this pivot highlights that skillful caution and tactical thinking are required, where one small adjustment can shift the whole trajectory; reading this as a timeline prevents over-weighting any single card. The likely direction shows in Advice through Snake (7), and it suggests that politics or complex incentives influence decisions once the pivot is met directly. Across the sequence, Fox (14) alongside Snake (7) reads as political complexity where tactical precision is essential, reinforcing a steady progression. Take one decisive operational step, then review what actually improved. ",
      "wordCount": 132
    },
    {
      "caseId": "money_gt",
      "setup": {
        "caseId": "money_gt",
        "subjectId": "money",
        "interpretationThemeId": "financial_pressure",
        "spreadType": "grand-tableau",
        "question": "How can I stabilize my finances while planning ahead?",
        "threeCardMode": "past-present-future",
        "significatorMode": "self"
      },
      "resolvedSubjectId": "money",
      "resolvedThemeId": "financial_pressure",
      "resolvedThemeLabel": "Financial Pressure",
      "selectedEntries": [
        {
          "technique": "card",
          "entryId": "card:money:2",
          "techniqueKey": "card:2",
          "score": 12.334,
          "selectedText": "Clover in Money highlights brief luck offers a manageable opening.",
          "summary": "Clover emphasizes luck in this context.",
          "alternatives": []
        },
        {
          "technique": "house",
          "entryId": "house:money:1",
          "techniqueKey": "house:1",
          "score": 11.828,
          "selectedText": "Rider House centers incoming momentum in a Money frame.",
          "summary": "Rider House acts as a contextual anchor.",
          "alternatives": []
        },
        {
          "technique": "pair",
          "entryId": "pair:money:21-34:fallback",
          "techniqueKey": "pair:21-34",
          "score": 12.4434,
          "selectedText": "Mountain + Fish in work context indicates structural blockers require persistence and planning and commercial and financial dynamics drive outcomes.",
          "summary": "Mountain and Fish create a contextual pair bridge.",
          "alternatives": []
        },
        {
          "technique": "diagonal",
          "entryId": "diagonal:money:primary",
          "techniqueKey": "diagonal:primary",
          "score": 9.84,
          "selectedText": "The primary diagonal in Money reveals a storyline crossing immediate and long-range influences.",
          "summary": null,
          "alternatives": []
        },
        {
          "technique": "knighting",
          "entryId": "knighting:money:significator",
          "techniqueKey": "knighting:significator",
          "score": 9.346,
          "selectedText": "Knighting from significator in Money highlights indirect triggers that can shift timing.",
          "summary": null,
          "alternatives": []
        },
        {
          "technique": "proximity",
          "entryId": "proximity:money:near",
          "techniqueKey": "proximity:near",
          "score": 10.178,
          "selectedText": "In Money, near proximity indicates how urgently this influence should be handled.",
          "summary": null,
          "alternatives": []
        },
        {
          "technique": "significator",
          "entryId": "significator:money:self",
          "techniqueKey": "significator:self",
          "score": 10.772,
          "selectedText": "Significator mode self in Money defines perspective and role framing before interpretation.",
          "summary": null,
          "alternatives": []
        }
      ],
      "rankingConcerns": [],
      "weakSummaryLines": [],
      "repeatedPhrasesInReading": [],
      "finalText": "\"How can I stabilize my finances while planning ahead\" comes into focus through Money in this Grand Tableau, with a financial pressure emphasis. From Ring House, Querent (29) frames the reading around the querent's agency and orientation. In context, the spread also suggests that professional identity and priorities need definition. A strong local signal comes from Fish (34) and Mountain (21), pointing toward this dynamic: work context indicates structural blockers require persistence and planning and commercial and financial dynamics drive outcomes; the pair gives practical context that keeps interpretation grounded; read the pair as one sentence: one card sets pressure, the other names response. A quieter structural current runs through Stars (16), Fish (34), Querent (29), Scythe (10) and Counterpart (28), Stork (17), House (4); knight touches at Book (26), Tower (19), Tree (5), Sun (31) add timing pressure around key choices. Timing-wise, Fish (34), Mountain (21), Stork (17), Ship (3) describe what is immediate, while Stars (16), Book (26), Letter (27), Tower (19) are more likely to shape the next wave. All strands point to a measured arc in how you're showing up, where patience and precision build the clearest outcome. Take one decisive operational step, then review what actually improved. ",
      "wordCount": 202
    },
    {
      "caseId": "money_3card",
      "setup": {
        "caseId": "money_3card",
        "subjectId": "money",
        "interpretationThemeId": "cashflow",
        "spreadType": "three-card",
        "question": "What is the near-term trajectory of my income and expenses?",
        "threeCardMode": "past-present-future",
        "significatorMode": "self"
      },
      "resolvedSubjectId": "money",
      "resolvedThemeId": "cashflow",
      "resolvedThemeLabel": "Cashflow",
      "selectedEntries": [
        {
          "technique": "card",
          "entryId": "card:money:21",
          "techniqueKey": "card:21",
          "score": 12.334,
          "selectedText": "Mountain in Money highlights an obstacle demands patient strategy.",
          "summary": "Mountain emphasizes obstacle in this context.",
          "alternatives": []
        },
        {
          "technique": "pair",
          "entryId": "pair:money:11-21:fallback",
          "techniqueKey": "pair:11-21",
          "score": 12.4214,
          "selectedText": "Whip + Mountain in work context indicates rework loops need a process reset and structural blockers require persistence and planning.",
          "summary": "Whip and Mountain create a contextual pair bridge.",
          "alternatives": []
        },
        {
          "technique": "diagonal",
          "entryId": "diagonal:money:primary",
          "techniqueKey": "diagonal:primary",
          "score": 9.84,
          "selectedText": "The primary diagonal in Money reveals a storyline crossing immediate and long-range influences.",
          "summary": null,
          "alternatives": []
        },
        {
          "technique": "knighting",
          "entryId": "knighting:money:significator",
          "techniqueKey": "knighting:significator",
          "score": 9.346,
          "selectedText": "Knighting from significator in Money highlights indirect triggers that can shift timing.",
          "summary": null,
          "alternatives": []
        },
        {
          "technique": "proximity",
          "entryId": "proximity:money:near",
          "techniqueKey": "proximity:near",
          "score": 10.178,
          "selectedText": "In Money, near proximity indicates how urgently this influence should be handled.",
          "summary": null,
          "alternatives": []
        },
        {
          "technique": "significator",
          "entryId": "significator:money:self",
          "techniqueKey": "significator:self",
          "score": 10.772,
          "selectedText": "Significator mode self in Money defines perspective and role framing before interpretation.",
          "summary": null,
          "alternatives": []
        }
      ],
      "rankingConcerns": [
        {
          "type": "pair",
          "message": "A stronger pair candidate scored higher than the selected pair context.",
          "selectedKey": "11-21",
          "strongerKey": "21-22",
          "delta": 1.153
        }
      ],
      "weakSummaryLines": [],
      "repeatedPhrasesInReading": [],
      "finalText": "Your question, \"What is the near-term trajectory of my income and expenses\", is read here through a Money lens with a cashflow emphasis. Past opens with Mountain (21), putting structural blockers require persistence and planning in focus and setting the emotional weather around your question; the middle position is especially important for how the outcome develops. Whip (11) in Present is the fulcrum of the spread, and its message is repetition can either refine or exhaust. Future closes with Crossroads (22), and the directional message is that strategic forks require tradeoff clarity when the pivot receives consistent attention. A clear subtext emerges through Whip (11) with Crossroads (22): a blend of repetition and choice; turn friction into intentional practice, while keeping in mind analysis paralysis, which gives the reading a coherent practical arc. Clarify one boundary in your workflow, then observe what pressure drops. ",
      "wordCount": 144
    },
    {
      "caseId": "home_gt",
      "setup": {
        "caseId": "home_gt",
        "subjectId": "home_family",
        "interpretationThemeId": "repair_or_renovation",
        "spreadType": "grand-tableau",
        "question": "What needs attention in my household and family rhythm?",
        "threeCardMode": "past-present-future",
        "significatorMode": "self"
      },
      "resolvedSubjectId": "home_family",
      "resolvedThemeId": "repair_or_renovation",
      "resolvedThemeLabel": "Repair OR Renovation",
      "selectedEntries": [
        {
          "technique": "card",
          "entryId": "card:home_family:35",
          "techniqueKey": "card:35",
          "score": 12.334,
          "selectedText": "Anchor in Home & Family highlights long-term commitment and steadiness are highlighted.",
          "summary": "Anchor emphasizes stability in this context.",
          "alternatives": []
        },
        {
          "technique": "house",
          "entryId": "house:home_family:1",
          "techniqueKey": "house:1",
          "score": 11.828,
          "selectedText": "Rider House centers incoming momentum in a Home & Family frame.",
          "summary": "Rider House acts as a contextual anchor.",
          "alternatives": []
        },
        {
          "technique": "pair",
          "entryId": "pair:home_family:15-24:fallback",
          "techniqueKey": "pair:15-24",
          "score": 12.472,
          "selectedText": "Bear + Heart blends power with love, inviting use leverage responsibly while staying aware of idealizing without boundaries.",
          "summary": "Bear and Heart create a contextual pair bridge.",
          "alternatives": []
        },
        {
          "technique": "diagonal",
          "entryId": "diagonal:home_family:primary",
          "techniqueKey": "diagonal:primary",
          "score": 10.47,
          "selectedText": "The primary diagonal in Home & Family reveals a storyline crossing immediate and long-range influences.",
          "summary": null,
          "alternatives": []
        },
        {
          "technique": "knighting",
          "entryId": "knighting:home_family:significator",
          "techniqueKey": "knighting:significator",
          "score": 9.976,
          "selectedText": "Knighting from significator in Home & Family highlights indirect triggers that can shift timing.",
          "summary": null,
          "alternatives": []
        },
        {
          "technique": "proximity",
          "entryId": "proximity:home_family:near",
          "techniqueKey": "proximity:near",
          "score": 10.178,
          "selectedText": "In Home & Family, near proximity indicates how urgently this influence should be handled.",
          "summary": null,
          "alternatives": []
        },
        {
          "technique": "significator",
          "entryId": "significator:home_family:self",
          "techniqueKey": "significator:self",
          "score": 10.772,
          "selectedText": "Significator mode self in Home & Family defines perspective and role framing before interpretation.",
          "summary": null,
          "alternatives": []
        }
      ],
      "rankingConcerns": [
        {
          "type": "pair",
          "message": "A stronger pair candidate scored higher than the selected pair context.",
          "selectedKey": "15-24",
          "strongerKey": "15-34",
          "delta": 2.002
        }
      ],
      "weakSummaryLines": [
        "This Grand Tableau approaches \"What needs attention in my household and family rhythm\" through Home & Family with a repair or renovation emphasis."
      ],
      "repeatedPhrasesInReading": [],
      "finalText": "This Grand Tableau approaches \"What needs attention in my household and family rhythm\" through Home & Family with a repair or renovation emphasis. The tableau centers on Querent (29) in Querent House. At this position, the message is that the querent's agency and orientation are central, and the wider layer suggests that your role and boundaries set the tone. The nearby pair of Heart (24) and Fish (34) reads as this: a blend of love and money; speak and act from authentic care, while keeping in mind untracked inflow/outflow. Behind the immediate storyline, the diagonal lines crossing Heart (24), Querent (29) and Dog (18), Coffin (8), Fish (34), together with knight moves to Counterpart (28), Cross (36), Whip (11), suggest stepwise development; this thread reads best as a sequence, not an isolated event. Timing-wise, Heart (24), Bear (15), Fish (34), Child (13) describe what is immediate, while Counterpart (28), Tree (5), Cross (36), Coffin (8) are more likely to shape the next wave; near cards describe what is active now, while the next ring shapes what follows. Seen together, these signals describe progression rather than verdict, and the meaning sharpens as events unfold. Make one deliberate adjustment, then let clarity catch up to action. ",
      "wordCount": 204
    },
    {
      "caseId": "growth_3card",
      "setup": {
        "caseId": "growth_3card",
        "subjectId": "personal_growth",
        "interpretationThemeId": "self_trust",
        "spreadType": "three-card",
        "question": "How do I strengthen confidence in my next decision?",
        "threeCardMode": "situation-challenge-advice",
        "significatorMode": "self"
      },
      "resolvedSubjectId": "personal_growth",
      "resolvedThemeId": "self_trust",
      "resolvedThemeLabel": "Self Trust",
      "selectedEntries": [
        {
          "technique": "card",
          "entryId": "card:personal_growth:27",
          "techniqueKey": "card:27",
          "score": 14.134,
          "selectedText": "Letter in Personal Growth highlights written communication and records are decisive.",
          "summary": "Letter emphasizes document in this context.",
          "alternatives": []
        },
        {
          "technique": "pair",
          "entryId": "pair:personal_growth:6-27:fallback",
          "techniqueKey": "pair:6-27",
          "score": 12.472,
          "selectedText": "Clouds + Letter blends uncertainty with document, inviting name unknowns before choosing direction while staying aware of vague or untracked communication.",
          "summary": "Clouds and Letter create a contextual pair bridge.",
          "alternatives": []
        },
        {
          "technique": "diagonal",
          "entryId": "diagonal:personal_growth:primary",
          "techniqueKey": "diagonal:primary",
          "score": 9.84,
          "selectedText": "The primary diagonal in Personal Growth reveals a storyline crossing immediate and long-range influences.",
          "summary": null,
          "alternatives": []
        },
        {
          "technique": "knighting",
          "entryId": "knighting:personal_growth:significator",
          "techniqueKey": "knighting:significator",
          "score": 9.346,
          "selectedText": "Knighting from significator in Personal Growth highlights indirect triggers that can shift timing.",
          "summary": null,
          "alternatives": []
        },
        {
          "technique": "proximity",
          "entryId": "proximity:personal_growth:near",
          "techniqueKey": "proximity:near",
          "score": 10.178,
          "selectedText": "In Personal Growth, near proximity indicates how urgently this influence should be handled.",
          "summary": null,
          "alternatives": []
        },
        {
          "technique": "significator",
          "entryId": "significator:personal_growth:self",
          "techniqueKey": "significator:self",
          "score": 10.772,
          "selectedText": "Significator mode self in Personal Growth defines perspective and role framing before interpretation.",
          "summary": null,
          "alternatives": []
        }
      ],
      "rankingConcerns": [],
      "weakSummaryLines": [],
      "repeatedPhrasesInReading": [],
      "finalText": "Using Personal Growth as the primary lens with a self trust emphasis, this 3-card addresses \"How do I strengthen confidence in my next decision\". What starts this sequence is Situation with Letter (27), bringing written clarity improves confidence directly to the front of the reading. At the pivot, Challenge brings Clouds (6) to the center, showing that clarity is partial and conditions are shifting and asking for careful adjustment over force; the middle position is especially important for how the outcome develops. Future movement in Advice and Lily (30) points to this: steady ethics stabilize long-term decisions, provided the central pressure is handled honestly. Letter (27) with Clouds (6) provides the strongest subtext, and it speaks to a blend of document and uncertainty; document clearly and follow up, while keeping in mind making absolute claims too early. Take one concrete step and let the next signal come from real outcomes. ",
      "wordCount": 150
    },
    {
      "caseId": "travel_gt",
      "setup": {
        "caseId": "travel_gt",
        "subjectId": "travel",
        "interpretationThemeId": "documents",
        "spreadType": "grand-tableau",
        "question": "How is my upcoming trip unfolding, especially documents and timing?",
        "threeCardMode": "past-present-future",
        "significatorMode": "self"
      },
      "resolvedSubjectId": "travel",
      "resolvedThemeId": "documents",
      "resolvedThemeLabel": "Documents",
      "selectedEntries": [
        {
          "technique": "card",
          "entryId": "card:travel:17",
          "techniqueKey": "card:17",
          "score": 12.334,
          "selectedText": "Stork in Travel highlights change is active and potentially beneficial.",
          "summary": "Stork emphasizes change in this context.",
          "alternatives": []
        },
        {
          "technique": "house",
          "entryId": "house:travel:1",
          "techniqueKey": "house:1",
          "score": 11.828,
          "selectedText": "Rider House centers incoming momentum in a Travel frame.",
          "summary": "Rider House acts as a contextual anchor.",
          "alternatives": []
        },
        {
          "technique": "pair",
          "entryId": "pair:travel:4-5:fallback",
          "techniqueKey": "pair:4-5",
          "score": 12.472,
          "selectedText": "House + Tree blends home with health, inviting strengthen routines and boundaries while staying aware of expecting immediate proof.",
          "summary": "House and Tree create a contextual pair bridge.",
          "alternatives": []
        },
        {
          "technique": "diagonal",
          "entryId": "diagonal:travel:primary",
          "techniqueKey": "diagonal:primary",
          "score": 9.84,
          "selectedText": "The primary diagonal in Travel reveals a storyline crossing immediate and long-range influences.",
          "summary": null,
          "alternatives": []
        },
        {
          "technique": "knighting",
          "entryId": "knighting:travel:significator",
          "techniqueKey": "knighting:significator",
          "score": 9.346,
          "selectedText": "Knighting from significator in Travel highlights indirect triggers that can shift timing.",
          "summary": null,
          "alternatives": []
        },
        {
          "technique": "proximity",
          "entryId": "proximity:travel:near",
          "techniqueKey": "proximity:near",
          "score": 10.178,
          "selectedText": "In Travel, near proximity indicates how urgently this influence should be handled.",
          "summary": null,
          "alternatives": []
        },
        {
          "technique": "significator",
          "entryId": "significator:travel:self",
          "techniqueKey": "significator:self",
          "score": 10.772,
          "selectedText": "Significator mode self in Travel defines perspective and role framing before interpretation.",
          "summary": null,
          "alternatives": []
        }
      ],
      "rankingConcerns": [],
      "weakSummaryLines": [
        "This Grand Tableau approaches \"How is my upcoming trip unfolding, especially documents and timing\" through Travel with a documents emphasis.",
        "Overall, the pattern suggests a calm cumulative shift in how you're showing up, with steady choices outperforming dramatic moves."
      ],
      "repeatedPhrasesInReading": [],
      "finalText": "This Grand Tableau approaches \"How is my upcoming trip unfolding, especially documents and timing\" through Travel with a documents emphasis. The tableau centers on Querent (29) in Fox House. At this position, the message is that the querent's agency and orientation are central, and the wider layer suggests that your role and boundaries set the tone; this house placement names where the issue is lived day to day. The nearby pair of Tree (5) and House (4) reads as this: a blend of health and home; commit to steady, restorative pacing, while keeping in mind overprotecting comfort zones; this pair matters because it shows how two active themes combine in real time. Behind the immediate storyline, the diagonal lines crossing Tree (5), Querent (29), Moon (32), Lily (30) and Letter (27), Mountain (21), Garden (20), together with knight moves to Snake (7), Dog (18), Ship (3), Child (13), suggest stepwise development. Timing-wise, Tree (5), House (4), Letter (27), Cross (36) describe what is immediate, while Snake (7), Dog (18), Anchor (35), Fish (34) are more likely to shape the next wave. Overall, the pattern suggests a calm cumulative shift in how you're showing up, with steady choices outperforming dramatic moves. Choose one grounded action, then reassess with fresh evidence. ",
      "wordCount": 209
    },
    {
      "caseId": "legal_gt",
      "setup": {
        "caseId": "legal_gt",
        "subjectId": "legal_admin",
        "interpretationThemeId": "documents",
        "spreadType": "grand-tableau",
        "question": "What should I watch in contracts and formal paperwork now?",
        "threeCardMode": "past-present-future",
        "significatorMode": "self"
      },
      "resolvedSubjectId": "legal_admin",
      "resolvedThemeId": "documents",
      "resolvedThemeLabel": "Documents",
      "selectedEntries": [
        {
          "technique": "card",
          "entryId": "card:legal_admin:6",
          "techniqueKey": "card:6",
          "score": 12.334,
          "selectedText": "Clouds in Legal / Admin highlights clarity is partial and conditions are shifting.",
          "summary": "Clouds emphasizes uncertainty in this context.",
          "alternatives": []
        },
        {
          "technique": "house",
          "entryId": "house:legal_admin:1",
          "techniqueKey": "house:1",
          "score": 11.828,
          "selectedText": "Rider House centers incoming momentum in a Legal / Admin frame.",
          "summary": "Rider House acts as a contextual anchor.",
          "alternatives": []
        },
        {
          "technique": "pair",
          "entryId": "pair:legal_admin:28-35:fallback",
          "techniqueKey": "pair:28-35",
          "score": 12.406,
          "selectedText": "Counterpart + Anchor in work context indicates key counterpart stakeholders shape outcomes and career direction and sustained effort are central.",
          "summary": "Counterpart and Anchor create a contextual pair bridge.",
          "alternatives": []
        },
        {
          "technique": "diagonal",
          "entryId": "diagonal:legal_admin:primary",
          "techniqueKey": "diagonal:primary",
          "score": 9.84,
          "selectedText": "The primary diagonal in Legal / Admin reveals a storyline crossing immediate and long-range influences.",
          "summary": null,
          "alternatives": []
        },
        {
          "technique": "knighting",
          "entryId": "knighting:legal_admin:significator",
          "techniqueKey": "knighting:significator",
          "score": 9.976,
          "selectedText": "Knighting from significator in Legal / Admin highlights indirect triggers that can shift timing.",
          "summary": null,
          "alternatives": []
        },
        {
          "technique": "proximity",
          "entryId": "proximity:legal_admin:near",
          "techniqueKey": "proximity:near",
          "score": 10.898,
          "selectedText": "In Legal / Admin, near proximity indicates how urgently this influence should be handled.",
          "summary": null,
          "alternatives": []
        },
        {
          "technique": "significator",
          "entryId": "significator:legal_admin:self",
          "techniqueKey": "significator:self",
          "score": 10.772,
          "selectedText": "Significator mode self in Legal / Admin defines perspective and role framing before interpretation.",
          "summary": null,
          "alternatives": []
        }
      ],
      "rankingConcerns": [
        {
          "type": "pair",
          "message": "A stronger pair candidate scored higher than the selected pair context.",
          "selectedKey": "28-35",
          "strongerKey": "24-28",
          "delta": 2.068
        }
      ],
      "weakSummaryLines": [
        "This Grand Tableau approaches \"What should I watch in contracts and formal paperwork now\" through Legal / Admin with a documents emphasis.",
        "Taken as a whole, this reads as a living process in how you're showing up, where pacing and consistency matter more than force."
      ],
      "repeatedPhrasesInReading": [],
      "finalText": "This Grand Tableau approaches \"What should I watch in contracts and formal paperwork now\" through Legal / Admin with a documents emphasis. Querent (29) sits in Child House, so the querent's agency and orientation becomes the center of gravity. The wider tone suggests that professional identity and priorities need definition; this house placement names where the issue is lived day to day. The nearby pair of Counterpart (28) and Heart (24) reads as this: collaboration that benefits from empathy; this pair matters because it shows how two active themes combine in real time. In the background, diagonals through Anchor (35), Querent (29), Stars (16), Fish (34) and Heart (24), Scythe (10), Tower (19), plus knighting links at Whip (11), Bouquet (9), Bear (15), Birds (12), show a process unfolding in stages rather than a single pivot. Read Anchor (35), Counterpart (28), Heart (24), Snake (7) as present-tense influence and Whip (11), Bouquet (9), Lily (30), Dog (18) as the sequence that forms right behind it. Taken as a whole, this reads as a living process in how you're showing up, where pacing and consistency matter more than force. Address one recurring friction point directly, then reassess with data. ",
      "wordCount": 198
    },
    {
      "caseId": "purpose_gt",
      "setup": {
        "caseId": "purpose_gt",
        "subjectId": "purpose_calling",
        "interpretationThemeId": "commitment",
        "spreadType": "grand-tableau",
        "question": "How do I commit to the path that feels deeply aligned?",
        "threeCardMode": "past-present-future",
        "significatorMode": "open"
      },
      "resolvedSubjectId": "purpose_calling",
      "resolvedThemeId": "commitment",
      "resolvedThemeLabel": "Commitment",
      "selectedEntries": [
        {
          "technique": "card",
          "entryId": "card:purpose_calling:5",
          "techniqueKey": "card:5",
          "score": 12.334,
          "selectedText": "Tree in Purpose / Calling highlights deep growth unfolds gradually.",
          "summary": "Tree emphasizes health in this context.",
          "alternatives": []
        },
        {
          "technique": "house",
          "entryId": "house:purpose_calling:1",
          "techniqueKey": "house:1",
          "score": 11.828,
          "selectedText": "Rider House centers incoming momentum in a Purpose / Calling frame.",
          "summary": "Rider House acts as a contextual anchor.",
          "alternatives": []
        },
        {
          "technique": "pair",
          "entryId": "pair:purpose_calling:4-33:fallback",
          "techniqueKey": "pair:4-33",
          "score": 12.4236,
          "selectedText": "House + Key blends home with solution, suggesting strengthen routines and boundaries while staying aware of locking onto one answer too soon.",
          "summary": "House and Key create a contextual pair bridge.",
          "alternatives": []
        },
        {
          "technique": "diagonal",
          "entryId": "diagonal:purpose_calling:primary",
          "techniqueKey": "diagonal:primary",
          "score": 10.47,
          "selectedText": "The primary diagonal in Purpose / Calling reveals a storyline crossing immediate and long-range influences.",
          "summary": null,
          "alternatives": []
        },
        {
          "technique": "knighting",
          "entryId": "knighting:purpose_calling:significator",
          "techniqueKey": "knighting:significator",
          "score": 9.346,
          "selectedText": "Knighting from significator in Purpose / Calling highlights indirect triggers that can shift timing.",
          "summary": null,
          "alternatives": []
        },
        {
          "technique": "proximity",
          "entryId": "proximity:purpose_calling:near",
          "techniqueKey": "proximity:near",
          "score": 10.178,
          "selectedText": "In Purpose / Calling, near proximity indicates how urgently this influence should be handled.",
          "summary": null,
          "alternatives": []
        },
        {
          "technique": "significator",
          "entryId": "significator:purpose_calling:open",
          "techniqueKey": "significator:open",
          "score": 10.772,
          "selectedText": "Significator mode open in Purpose / Calling defines perspective and role framing before interpretation.",
          "summary": null,
          "alternatives": []
        }
      ],
      "rankingConcerns": [
        {
          "type": "pair",
          "message": "A stronger pair candidate scored higher than the selected pair context.",
          "selectedKey": "4-33",
          "strongerKey": "21-33",
          "delta": 1.15
        }
      ],
      "weakSummaryLines": [],
      "repeatedPhrasesInReading": [
        "Seen together, these signals describe progression rather than verdict, and the meaning sharpens as events unfold."
      ],
      "finalText": "Using Purpose / Calling as the primary lens with a commitment emphasis, this Grand Tableau addresses \"How do I commit to the path that feels deeply aligned\". The tableau centers on Querent (29) in Bear House. At this position, the message is that the querent's agency and orientation are central, and the wider layer suggests that your role and boundaries set the tone; the center card shows not just what matters, but where it asks to be addressed. The nearby pair of Key (33) and Mountain (21) reads as this: persistence reveals the exact solution. In the background, diagonals through House (4), Querent (29), Bouquet (9), Counterpart (28) and Lily (30), Child (13), Anchor (35), plus knighting links at Whip (11), Mice (23), Stars (16), Cross (36), show a process unfolding in stages rather than a single pivot. The near field, House (4), Key (33), Lily (30), Mountain (21), speaks to current pressure, and Whip (11), Mice (23), Clover (2), Coffin (8) points to what gathers just after; proximity keeps the timing clear: immediate pressure first, broader movement second. Seen together, these signals describe progression rather than verdict, and the meaning sharpens as events unfold. Take one concrete step and let the next signal come from real outcomes. ",
      "wordCount": 208
    },
    {
      "caseId": "purpose_3card",
      "setup": {
        "caseId": "purpose_3card",
        "subjectId": "purpose_calling",
        "interpretationThemeId": "right_path",
        "spreadType": "three-card",
        "question": "What is the next right step in my calling?",
        "threeCardMode": "past-present-future",
        "significatorMode": "open"
      },
      "resolvedSubjectId": "purpose_calling",
      "resolvedThemeId": "right_path",
      "resolvedThemeLabel": "Right Path",
      "selectedEntries": [
        {
          "technique": "card",
          "entryId": "card:purpose_calling:34",
          "techniqueKey": "card:34",
          "score": 12.334,
          "selectedText": "Fish in Purpose / Calling highlights resources and flow patterns become central.",
          "summary": "Fish emphasizes money in this context.",
          "alternatives": []
        },
        {
          "technique": "pair",
          "entryId": "pair:purpose_calling:5-34:fallback",
          "techniqueKey": "pair:5-34",
          "score": 12.472,
          "selectedText": "Tree + Fish blends health with money, inviting commit to steady, restorative pacing while staying aware of untracked inflow/outflow.",
          "summary": "Tree and Fish create a contextual pair bridge.",
          "alternatives": []
        },
        {
          "technique": "diagonal",
          "entryId": "diagonal:purpose_calling:primary",
          "techniqueKey": "diagonal:primary",
          "score": 9.84,
          "selectedText": "The primary diagonal in Purpose / Calling reveals a storyline crossing immediate and long-range influences.",
          "summary": null,
          "alternatives": []
        },
        {
          "technique": "knighting",
          "entryId": "knighting:purpose_calling:significator",
          "techniqueKey": "knighting:significator",
          "score": 9.346,
          "selectedText": "Knighting from significator in Purpose / Calling highlights indirect triggers that can shift timing.",
          "summary": null,
          "alternatives": []
        },
        {
          "technique": "proximity",
          "entryId": "proximity:purpose_calling:near",
          "techniqueKey": "proximity:near",
          "score": 10.898,
          "selectedText": "In Purpose / Calling, near proximity indicates how urgently this influence should be handled.",
          "summary": null,
          "alternatives": []
        },
        {
          "technique": "significator",
          "entryId": "significator:purpose_calling:open",
          "techniqueKey": "significator:open",
          "score": 11.312,
          "selectedText": "Significator mode open in Purpose / Calling defines perspective and role framing before interpretation.",
          "summary": null,
          "alternatives": []
        }
      ],
      "rankingConcerns": [],
      "weakSummaryLines": [
        "This 3-card approaches \"What is the next right step in my calling\" through Purpose / Calling with a right path emphasis."
      ],
      "repeatedPhrasesInReading": [],
      "finalText": "This 3-card approaches \"What is the next right step in my calling\" through Purpose / Calling with a right path emphasis. Past opens with Fish (34), putting resource flow is dynamic and responsive in focus and setting the emotional weather around your question. Present carries Tree (5), and this pivot highlights that deep growth unfolds gradually, where one small adjustment can shift the whole trajectory. The likely direction shows in Future through Coffin (8), and it suggests that release an outdated pattern gracefully once the pivot is met directly; the middle position is especially important for how the outcome develops. A clear subtext emerges through Fish (34) with Tree (5): a blend of money and health; monitor movement and align values, while keeping in mind expecting immediate proof, which gives the reading a coherent practical arc. Choose one grounded action, then reassess with fresh evidence. ",
      "wordCount": 145
    }
  ],
  "aggregate": {
    "sampleCount": 14,
    "repeatedPhrases": [
      {
        "sentence": "Seen together, these signals describe progression rather than verdict, and the meaning sharpens as events unfold.",
        "count": 3
      }
    ],
    "overusedOpenings": [
      {
        "opening": "the tableau centers",
        "count": 4
      },
      {
        "opening": "at this position,",
        "count": 4
      },
      {
        "opening": "a clear subtext",
        "count": 4
      },
      {
        "opening": "the nearby pair",
        "count": 4
      }
    ],
    "weakSummaryLines": [
      {
        "caseId": "general_gt",
        "line": "Taken as a whole, this reads as a living process in the dynamic between you and the counterpart, where pacing and consistency matter more than force."
      },
      {
        "caseId": "love_gt",
        "line": "Overall, the pattern suggests a calm cumulative shift in the relationship itself, with steady choices outperforming dramatic moves."
      },
      {
        "caseId": "home_gt",
        "line": "This Grand Tableau approaches \"What needs attention in my household and family rhythm\" through Home & Family with a repair or renovation emphasis."
      },
      {
        "caseId": "travel_gt",
        "line": "This Grand Tableau approaches \"How is my upcoming trip unfolding, especially documents and timing\" through Travel with a documents emphasis."
      },
      {
        "caseId": "travel_gt",
        "line": "Overall, the pattern suggests a calm cumulative shift in how you're showing up, with steady choices outperforming dramatic moves."
      },
      {
        "caseId": "legal_gt",
        "line": "This Grand Tableau approaches \"What should I watch in contracts and formal paperwork now\" through Legal / Admin with a documents emphasis."
      },
      {
        "caseId": "legal_gt",
        "line": "Taken as a whole, this reads as a living process in how you're showing up, where pacing and consistency matter more than force."
      },
      {
        "caseId": "purpose_3card",
        "line": "This 3-card approaches \"What is the next right step in my calling\" through Purpose / Calling with a right path emphasis."
      }
    ],
    "rankingConcerns": [
      {
        "type": "pair",
        "message": "A stronger pair candidate scored higher than the selected pair context.",
        "selectedKey": "14-28",
        "strongerKey": "7-14",
        "delta": 1.168
      },
      {
        "type": "pair",
        "message": "A stronger pair candidate scored higher than the selected pair context.",
        "selectedKey": "11-21",
        "strongerKey": "21-22",
        "delta": 1.153
      },
      {
        "type": "pair",
        "message": "A stronger pair candidate scored higher than the selected pair context.",
        "selectedKey": "15-24",
        "strongerKey": "15-34",
        "delta": 2.002
      },
      {
        "type": "pair",
        "message": "A stronger pair candidate scored higher than the selected pair context.",
        "selectedKey": "28-35",
        "strongerKey": "24-28",
        "delta": 2.068
      },
      {
        "type": "pair",
        "message": "A stronger pair candidate scored higher than the selected pair context.",
        "selectedKey": "4-33",
        "strongerKey": "21-33",
        "delta": 1.15
      }
    ],
    "mostFrequentEntries": [
      {
        "entryId": "diagonal:love:primary",
        "technique": "diagonal",
        "count": 3
      },
      {
        "entryId": "knighting:love:significator",
        "technique": "knighting",
        "count": 3
      },
      {
        "entryId": "proximity:love:near",
        "technique": "proximity",
        "count": 3
      },
      {
        "entryId": "house:love:1",
        "technique": "house",
        "count": 2
      },
      {
        "entryId": "significator:love:relationship",
        "technique": "significator",
        "count": 2
      },
      {
        "entryId": "diagonal:work:primary",
        "technique": "diagonal",
        "count": 2
      },
      {
        "entryId": "knighting:work:significator",
        "technique": "knighting",
        "count": 2
      },
      {
        "entryId": "proximity:work:near",
        "technique": "proximity",
        "count": 2
      },
      {
        "entryId": "significator:work:self",
        "technique": "significator",
        "count": 2
      },
      {
        "entryId": "diagonal:money:primary",
        "technique": "diagonal",
        "count": 2
      },
      {
        "entryId": "knighting:money:significator",
        "technique": "knighting",
        "count": 2
      },
      {
        "entryId": "proximity:money:near",
        "technique": "proximity",
        "count": 2
      },
      {
        "entryId": "significator:money:self",
        "technique": "significator",
        "count": 2
      },
      {
        "entryId": "diagonal:purpose_calling:primary",
        "technique": "diagonal",
        "count": 2
      },
      {
        "entryId": "knighting:purpose_calling:significator",
        "technique": "knighting",
        "count": 2
      },
      {
        "entryId": "proximity:purpose_calling:near",
        "technique": "proximity",
        "count": 2
      },
      {
        "entryId": "significator:purpose_calling:open",
        "technique": "significator",
        "count": 2
      },
      {
        "entryId": "card:love:24",
        "technique": "card",
        "count": 1
      },
      {
        "entryId": "pair:love:17-27:fallback",
        "technique": "pair",
        "count": 1
      },
      {
        "entryId": "significator:love:open",
        "technique": "significator",
        "count": 1
      }
    ],
    "underusedNeverSelected": [
      {
        "entryId": "pair:general_reading:28-29",
        "technique": "pair",
        "count": 0,
        "weight": 1.12
      },
      {
        "entryId": "pair:general_reading:22-29",
        "technique": "pair",
        "count": 0,
        "weight": 1.12
      },
      {
        "entryId": "pair:general_reading:29-33",
        "technique": "pair",
        "count": 0,
        "weight": 1.12
      },
      {
        "entryId": "pair:general_reading:21-33",
        "technique": "pair",
        "count": 0,
        "weight": 1.12
      },
      {
        "entryId": "pair:general_reading:31-33",
        "technique": "pair",
        "count": 0,
        "weight": 1.12
      },
      {
        "entryId": "pair:general_reading:33-36",
        "technique": "pair",
        "count": 0,
        "weight": 1.12
      },
      {
        "entryId": "pair:general_reading:27-29",
        "technique": "pair",
        "count": 0,
        "weight": 1.12
      },
      {
        "entryId": "pair:general_reading:10-36",
        "technique": "pair",
        "count": 0,
        "weight": 1.12
      },
      {
        "entryId": "pair:general_reading:34-36",
        "technique": "pair",
        "count": 0,
        "weight": 1.12
      },
      {
        "entryId": "pair:general_reading:35-36",
        "technique": "pair",
        "count": 0,
        "weight": 1.12
      },
      {
        "entryId": "pair:general_reading:6-33",
        "technique": "pair",
        "count": 0,
        "weight": 1.12
      },
      {
        "entryId": "pair:general_reading:19-33",
        "technique": "pair",
        "count": 0,
        "weight": 1.12
      },
      {
        "entryId": "pair:general_reading:26-33",
        "technique": "pair",
        "count": 0,
        "weight": 1.12
      },
      {
        "entryId": "pair:general_reading:32-36",
        "technique": "pair",
        "count": 0,
        "weight": 1.12
      },
      {
        "entryId": "pair:general_reading:21-29",
        "technique": "pair",
        "count": 0,
        "weight": 1.12
      },
      {
        "entryId": "pair:general_reading:29-31",
        "technique": "pair",
        "count": 0,
        "weight": 1.12
      },
      {
        "entryId": "pair:general_reading:29-36",
        "technique": "pair",
        "count": 0,
        "weight": 1.12
      },
      {
        "entryId": "pair:general_reading:16-31",
        "technique": "pair",
        "count": 0,
        "weight": 1.12
      },
      {
        "entryId": "pair:general_reading:24-28",
        "technique": "pair",
        "count": 0,
        "weight": 1.12
      },
      {
        "entryId": "pair:general_reading:5-21",
        "technique": "pair",
        "count": 0,
        "weight": 1.12
      },
      {
        "entryId": "pair:general_reading:1-29",
        "technique": "pair",
        "count": 0,
        "weight": 1.12
      },
      {
        "entryId": "pair:general_reading:7-29",
        "technique": "pair",
        "count": 0,
        "weight": 1.12
      },
      {
        "entryId": "pair:general_reading:8-29",
        "technique": "pair",
        "count": 0,
        "weight": 1.12
      },
      {
        "entryId": "pair:general_reading:10-29",
        "technique": "pair",
        "count": 0,
        "weight": 1.12
      },
      {
        "entryId": "pair:general_reading:14-29",
        "technique": "pair",
        "count": 0,
        "weight": 1.12
      },
      {
        "entryId": "pair:general_reading:15-29",
        "technique": "pair",
        "count": 0,
        "weight": 1.12
      },
      {
        "entryId": "pair:general_reading:16-29",
        "technique": "pair",
        "count": 0,
        "weight": 1.12
      },
      {
        "entryId": "pair:general_reading:23-29",
        "technique": "pair",
        "count": 0,
        "weight": 1.12
      },
      {
        "entryId": "pair:general_reading:24-29",
        "technique": "pair",
        "count": 0,
        "weight": 1.12
      },
      {
        "entryId": "pair:general_reading:25-29",
        "technique": "pair",
        "count": 0,
        "weight": 1.12
      },
      {
        "entryId": "pair:general_reading:29-34",
        "technique": "pair",
        "count": 0,
        "weight": 1.12
      },
      {
        "entryId": "pair:general_reading:29-35",
        "technique": "pair",
        "count": 0,
        "weight": 1.12
      },
      {
        "entryId": "pair:general_reading:1-10",
        "technique": "pair",
        "count": 0,
        "weight": 1.12
      },
      {
        "entryId": "pair:general_reading:2-31",
        "technique": "pair",
        "count": 0,
        "weight": 1.12
      },
      {
        "entryId": "pair:general_reading:7-14",
        "technique": "pair",
        "count": 0,
        "weight": 1.12
      },
      {
        "entryId": "pair:general_reading:8-35",
        "technique": "pair",
        "count": 0,
        "weight": 1.12
      },
      {
        "entryId": "pair:general_reading:14-15",
        "technique": "pair",
        "count": 0,
        "weight": 1.12
      },
      {
        "entryId": "pair:general_reading:15-34",
        "technique": "pair",
        "count": 0,
        "weight": 1.12
      },
      {
        "entryId": "pair:general_reading:17-22",
        "technique": "pair",
        "count": 0,
        "weight": 1.12
      },
      {
        "entryId": "pair:general_reading:20-31",
        "technique": "pair",
        "count": 0,
        "weight": 1.12
      }
    ],
    "underusedRarelySelected": [
      {
        "entryId": "card:love:4",
        "technique": "card",
        "count": 1,
        "weight": 1.05
      },
      {
        "entryId": "card:love:12",
        "technique": "card",
        "count": 1,
        "weight": 1.05
      },
      {
        "entryId": "card:love:24",
        "technique": "card",
        "count": 1,
        "weight": 1.05
      },
      {
        "entryId": "card:work:12",
        "technique": "card",
        "count": 1,
        "weight": 1.05
      },
      {
        "entryId": "card:work:28",
        "technique": "card",
        "count": 1,
        "weight": 1.05
      },
      {
        "entryId": "card:money:2",
        "technique": "card",
        "count": 1,
        "weight": 1.05
      },
      {
        "entryId": "card:money:21",
        "technique": "card",
        "count": 1,
        "weight": 1.05
      },
      {
        "entryId": "card:home_family:35",
        "technique": "card",
        "count": 1,
        "weight": 1.05
      },
      {
        "entryId": "card:personal_growth:27",
        "technique": "card",
        "count": 1,
        "weight": 1.05
      },
      {
        "entryId": "card:health:28",
        "technique": "card",
        "count": 1,
        "weight": 1.05
      },
      {
        "entryId": "card:travel:17",
        "technique": "card",
        "count": 1,
        "weight": 1.05
      },
      {
        "entryId": "card:legal_admin:6",
        "technique": "card",
        "count": 1,
        "weight": 1.05
      },
      {
        "entryId": "card:purpose_calling:5",
        "technique": "card",
        "count": 1,
        "weight": 1.05
      },
      {
        "entryId": "card:purpose_calling:34",
        "technique": "card",
        "count": 1,
        "weight": 1.05
      },
      {
        "entryId": "house:work:1",
        "technique": "house",
        "count": 1,
        "weight": 1
      },
      {
        "entryId": "house:money:1",
        "technique": "house",
        "count": 1,
        "weight": 1
      },
      {
        "entryId": "house:home_family:1",
        "technique": "house",
        "count": 1,
        "weight": 1
      },
      {
        "entryId": "house:travel:1",
        "technique": "house",
        "count": 1,
        "weight": 1
      },
      {
        "entryId": "house:legal_admin:1",
        "technique": "house",
        "count": 1,
        "weight": 1
      },
      {
        "entryId": "house:purpose_calling:1",
        "technique": "house",
        "count": 1,
        "weight": 1
      },
      {
        "entryId": "significator:love:open",
        "technique": "significator",
        "count": 1,
        "weight": 0.9
      },
      {
        "entryId": "significator:home_family:self",
        "technique": "significator",
        "count": 1,
        "weight": 0.9
      },
      {
        "entryId": "significator:personal_growth:self",
        "technique": "significator",
        "count": 1,
        "weight": 0.9
      },
      {
        "entryId": "significator:health:self",
        "technique": "significator",
        "count": 1,
        "weight": 0.9
      },
      {
        "entryId": "significator:travel:self",
        "technique": "significator",
        "count": 1,
        "weight": 0.9
      },
      {
        "entryId": "significator:legal_admin:self",
        "technique": "significator",
        "count": 1,
        "weight": 0.9
      },
      {
        "entryId": "proximity:home_family:near",
        "technique": "proximity",
        "count": 1,
        "weight": 0.88
      },
      {
        "entryId": "proximity:personal_growth:near",
        "technique": "proximity",
        "count": 1,
        "weight": 0.88
      },
      {
        "entryId": "proximity:health:near",
        "technique": "proximity",
        "count": 1,
        "weight": 0.88
      },
      {
        "entryId": "proximity:travel:near",
        "technique": "proximity",
        "count": 1,
        "weight": 0.88
      },
      {
        "entryId": "proximity:legal_admin:near",
        "technique": "proximity",
        "count": 1,
        "weight": 0.88
      },
      {
        "entryId": "diagonal:home_family:primary",
        "technique": "diagonal",
        "count": 1,
        "weight": 0.86
      },
      {
        "entryId": "diagonal:personal_growth:primary",
        "technique": "diagonal",
        "count": 1,
        "weight": 0.86
      },
      {
        "entryId": "diagonal:health:primary",
        "technique": "diagonal",
        "count": 1,
        "weight": 0.86
      },
      {
        "entryId": "diagonal:travel:primary",
        "technique": "diagonal",
        "count": 1,
        "weight": 0.86
      },
      {
        "entryId": "diagonal:legal_admin:primary",
        "technique": "diagonal",
        "count": 1,
        "weight": 0.86
      },
      {
        "entryId": "knighting:home_family:significator",
        "technique": "knighting",
        "count": 1,
        "weight": 0.82
      },
      {
        "entryId": "knighting:personal_growth:significator",
        "technique": "knighting",
        "count": 1,
        "weight": 0.82
      },
      {
        "entryId": "knighting:health:significator",
        "technique": "knighting",
        "count": 1,
        "weight": 0.82
      },
      {
        "entryId": "knighting:travel:significator",
        "technique": "knighting",
        "count": 1,
        "weight": 0.82
      }
    ],
    "coverageSnapshot": {
      "totalEntries": 2128,
      "byTechnique": {
        "card": 576,
        "house": 576,
        "pair": 768,
        "diagonal": 32,
        "knighting": 64,
        "proximity": 48,
        "significator": 64
      },
      "themesWithZeroEntries": []
    }
  }
}